{
  "axial": [
    {
      "index": 1,
      "annotations": []
    },
    {
      "index": 2,
      "annotations": []
    },
    {
      "index": 3,
      "annotations": []
    },
    {
      "index": 4,
      "annotations": []
    },
    {
      "index": 5,
      "annotations": []
    },
    {
      "index": 6,
      "annotations": []
    },
    {
      "index": 7,
      "annotations": []
    },
    {
      "index": 8,
      "annotations": []
    },
    {
      "index": 9,
      "annotations": []
    },
    {
      "index": 10,
      "annotations": []
    },
    {
      "index": 11,
      "annotations": []
    },
    {
      "index": 12,
      "annotations": []
    },
    {
      "index": 13,
      "annotations": []
    },
    {
      "index": 14,
      "annotations": []
    },
    {
      "index": 15,
      "annotations": []
    },
    {
      "index": 16,
      "annotations": []
    },
    {
      "index": 17,
      "annotations": []
    },
    {
      "index": 18,
      "annotations": []
    },
    {
      "index": 19,
      "annotations": []
    },
    {
      "index": 20,
      "annotations": []
    },
    {
      "index": 21,
      "annotations": []
    },
    {
      "index": 22,
      "annotations": []
    },
    {
      "index": 23,
      "annotations": []
    },
    {
      "index": 24,
      "annotations": []
    },
    {
      "index": 25,
      "annotations": []
    },
    {
      "index": 26,
      "annotations": []
    },
    {
      "index": 27,
      "annotations": []
    },
    {
      "index": 28,
      "annotations": []
    },
    {
      "index": 29,
      "annotations": []
    },
    {
      "index": 30,
      "annotations": []
    },
    {
      "index": 31,
      "annotations": []
    },
    {
      "index": 32,
      "annotations": []
    },
    {
      "index": 33,
      "annotations": []
    },
    {
      "index": 34,
      "annotations": []
    },
    {
      "index": 35,
      "annotations": []
    },
    {
      "index": 36,
      "annotations": []
    },
    {
      "index": 37,
      "annotations": []
    },
    {
      "index": 38,
      "annotations": []
    },
    {
      "index": 39,
      "annotations": []
    },
    {
      "index": 40,
      "annotations": []
    },
    {
      "index": 41,
      "annotations": []
    },
    {
      "index": 42,
      "annotations": []
    },
    {
      "index": 43,
      "annotations": []
    },
    {
      "index": 44,
      "annotations": []
    },
    {
      "index": 45,
      "annotations": []
    },
    {
      "index": 46,
      "annotations": []
    },
    {
      "index": 47,
      "annotations": []
    },
    {
      "index": 48,
      "annotations": []
    },
    {
      "index": 49,
      "annotations": []
    },
    {
      "index": 50,
      "annotations": []
    },
    {
      "index": 51,
      "annotations": []
    },
    {
      "index": 52,
      "annotations": []
    },
    {
      "index": 53,
      "annotations": []
    },
    {
      "index": 54,
      "annotations": []
    },
    {
      "index": 55,
      "annotations": []
    },
    {
      "index": 56,
      "annotations": []
    },
    {
      "index": 57,
      "annotations": []
    },
    {
      "index": 58,
      "annotations": []
    },
    {
      "index": 59,
      "annotations": []
    },
    {
      "index": 60,
      "annotations": []
    },
    {
      "index": 61,
      "annotations": []
    },
    {
      "index": 62,
      "annotations": [{"index": 1}]
    },
    {
      "index": 63,
      "annotations": []
    },
    {
      "index": 64,
      "annotations": [{"index": 1}]
    },
    {
      "index": 65,
      "annotations": []
    },
    {
      "index": 66,
      "annotations": [{"index": 1}]
    },
    {
      "index": 67,
      "annotations": []
    },
    {
      "index": 68,
      "annotations": [{"index": 1}]
    },
    {
      "index": 69,
      "annotations": []
    },
    {
      "index": 70,
      "annotations": [{"index": 1}]
    },
    {
      "index": 71,
      "annotations": []
    },
    {
      "index": 72,
      "annotations": [{"index": 1}]
    },
    {
      "index": 73,
      "annotations": []
    },
    {
      "index": 74,
      "annotations": [{"index": 1}]
    },
    {
      "index": 75,
      "annotations": []
    },
    {
      "index": 76,
      "annotations": [{"index": 1}]
    },
    {
      "index": 77,
      "annotations": []
    },
    {
      "index": 78,
      "annotations": [{"index": 1}]
    },
    {
      "index": 79,
      "annotations": []
    },
    {
      "index": 80,
      "annotations": [{"index": 1}]
    },
    {
      "index": 81,
      "annotations": []
    },
    {
      "index": 82,
      "annotations": [{"index": 1}]
    },
    {
      "index": 83,
      "annotations": []
    },
    {
      "index": 84,
      "annotations": [{"index": 1}]
    },
    {
      "index": 85,
      "annotations": []
    },
    {
      "index": 86,
      "annotations": [{"index": 1}]
    },
    {
      "index": 87,
      "annotations": []
    },
    {
      "index": 88,
      "annotations": [{"index": 1}]
    },
    {
      "index": 89,
      "annotations": []
    },
    {
      "index": 90,
      "annotations": [{"index": 1}]
    },
    {
      "index": 91,
      "annotations": []
    },
    {
      "index": 92,
      "annotations": [{"index": 1}]
    },
    {
      "index": 93,
      "annotations": []
    },
    {
      "index": 94,
      "annotations": [{"index": 1}]
    },
    {
      "index": 95,
      "annotations": []
    },
    {
      "index": 96,
      "annotations": [{"index": 1}]
    },
    {
      "index": 97,
      "annotations": []
    },
    {
      "index": 98,
      "annotations": [{"index": 1}]
    },
    {
      "index": 99,
      "annotations": []
    },
    {
      "index": 100,
      "annotations": [{"index": 1}]
    },
    {
      "index": 101,
      "annotations": []
    },
    {
      "index": 102,
      "annotations": [{"index": 1}]
    },
    {
      "index": 103,
      "annotations": []
    },
    {
      "index": 104,
      "annotations": [{"index": 1}]
    },
    {
      "index": 105,
      "annotations": []
    },
    {
      "index": 106,
      "annotations": [{"index": 1}]
    },
    {
      "index": 107,
      "annotations": []
    },
    {
      "index": 108,
      "annotations": [{"index": 1}]
    },
    {
      "index": 109,
      "annotations": []
    },
    {
      "index": 110,
      "annotations": [{"index": 1}]
    },
    {
      "index": 111,
      "annotations": []
    },
    {
      "index": 112,
      "annotations": [{"index": 1}]
    },
    {
      "index": 113,
      "annotations": []
    },
    {
      "index": 114,
      "annotations": [{"index": 1}]
    },
    {
      "index": 115,
      "annotations": []
    },
    {
      "index": 116,
      "annotations": [{"index": 1}]
    },
    {
      "index": 117,
      "annotations": []
    },
    {
      "index": 118,
      "annotations": [{"index": 1}]
    },
    {
      "index": 119,
      "annotations": []
    },
    {
      "index": 120,
      "annotations": [{"index": 1}]
    },
    {
      "index": 121,
      "annotations": []
    },
    {
      "index": 122,
      "annotations": []
    },
    {
      "index": 123,
      "annotations": []
    },
    {
      "index": 124,
      "annotations": [{"index": 1}]
    },
    {
      "index": 125,
      "annotations": []
    },
    {
      "index": 126,
      "annotations": [{"index": 1}]
    },
    {
      "index": 127,
      "annotations": []
    },
    {
      "index": 128,
      "annotations": [{"index": 1}]
    },
    {
      "index": 129,
      "annotations": []
    },
    {
      "index": 130,
      "annotations": [{"index": 1}]
    },
    {
      "index": 131,
      "annotations": []
    },
    {
      "index": 132,
      "annotations": [{"index": 1}]
    },
    {
      "index": 133,
      "annotations": []
    },
    {
      "index": 134,
      "annotations": [{"index": 1}]
    },
    {
      "index": 135,
      "annotations": []
    },
    {
      "index": 136,
      "annotations": [{"index": 1}]
    },
    {
      "index": 137,
      "annotations": []
    },
    {
      "index": 138,
      "annotations": [{"index": 1}]
    },
    {
      "index": 139,
      "annotations": []
    },
    {
      "index": 140,
      "annotations": [{"index": 1}]
    },
    {
      "index": 141,
      "annotations": []
    },
    {
      "index": 142,
      "annotations": [{"index": 1}]
    },
    {
      "index": 143,
      "annotations": []
    },
    {
      "index": 144,
      "annotations": []
    },
    {
      "index": 145,
      "annotations": []
    },
    {
      "index": 146,
      "annotations": [{"index": 1}]
    },
    {
      "index": 147,
      "annotations": []
    },
    {
      "index": 148,
      "annotations": []
    },
    {
      "index": 149,
      "annotations": []
    },
    {
      "index": 150,
      "annotations": []
    },
    {
      "index": 151,
      "annotations": []
    },
    {
      "index": 152,
      "annotations": []
    },
    {
      "index": 153,
      "annotations": []
    },
    {
      "index": 154,
      "annotations": []
    },
    {
      "index": 155,
      "annotations": []
    },
    {
      "index": 156,
      "annotations": []
    },
    {
      "index": 157,
      "annotations": []
    },
    {
      "index": 158,
      "annotations": []
    },
    {
      "index": 159,
      "annotations": []
    },
    {
      "index": 160,
      "annotations": []
    },
    {
      "index": 161,
      "annotations": []
    },
    {
      "index": 162,
      "annotations": []
    },
    {
      "index": 163,
      "annotations": []
    },
    {
      "index": 164,
      "annotations": []
    },
    {
      "index": 165,
      "annotations": []
    },
    {
      "index": 166,
      "annotations": []
    },
    {
      "index": 167,
      "annotations": []
    },
    {
      "index": 168,
      "annotations": []
    },
    {
      "index": 169,
      "annotations": []
    },
    {
      "index": 170,
      "annotations": []
    },
    {
      "index": 171,
      "annotations": []
    },
    {
      "index": 172,
      "annotations": []
    },
    {
      "index": 173,
      "annotations": []
    },
    {
      "index": 174,
      "annotations": []
    },
    {
      "index": 175,
      "annotations": []
    },
    {
      "index": 176,
      "annotations": []
    },
    {
      "index": 177,
      "annotations": []
    },
    {
      "index": 178,
      "annotations": []
    }
  ],
  "coronal": [
    {
      "index": 1,
      "annotations": []
    },
    {
      "index": 2,
      "annotations": []
    },
    {
      "index": 3,
      "annotations": []
    },
    {
      "index": 4,
      "annotations": []
    },
    {
      "index": 5,
      "annotations": []
    },
    {
      "index": 6,
      "annotations": []
    },
    {
      "index": 7,
      "annotations": []
    },
    {
      "index": 8,
      "annotations": []
    },
    {
      "index": 9,
      "annotations": []
    },
    {
      "index": 10,
      "annotations": []
    },
    {
      "index": 11,
      "annotations": []
    },
    {
      "index": 12,
      "annotations": []
    },
    {
      "index": 13,
      "annotations": []
    },
    {
      "index": 14,
      "annotations": []
    },
    {
      "index": 15,
      "annotations": []
    },
    {
      "index": 16,
      "annotations": []
    },
    {
      "index": 17,
      "annotations": []
    },
    {
      "index": 18,
      "annotations": []
    },
    {
      "index": 19,
      "annotations": []
    },
    {
      "index": 20,
      "annotations": []
    },
    {
      "index": 21,
      "annotations": []
    },
    {
      "index": 22,
      "annotations": []
    },
    {
      "index": 23,
      "annotations": []
    },
    {
      "index": 24,
      "annotations": []
    },
    {
      "index": 25,
      "annotations": []
    },
    {
      "index": 26,
      "annotations": []
    },
    {
      "index": 27,
      "annotations": []
    },
    {
      "index": 28,
      "annotations": []
    },
    {
      "index": 29,
      "annotations": []
    },
    {
      "index": 30,
      "annotations": []
    },
    {
      "index": 31,
      "annotations": [{"index": 1}]
    },
    {
      "index": 32,
      "annotations": []
    },
    {
      "index": 33,
      "annotations": [{"index": 1}]
    },
    {
      "index": 34,
      "annotations": []
    },
    {
      "index": 35,
      "annotations": [{"index": 1}]
    },
    {
      "index": 36,
      "annotations": []
    },
    {
      "index": 37,
      "annotations": [{"index": 1}]
    },
    {
      "index": 38,
      "annotations": []
    },
    {
      "index": 39,
      "annotations": [{"index": 1}]
    },
    {
      "index": 40,
      "annotations": []
    },
    {
      "index": 41,
      "annotations": [{"index": 1}]
    },
    {
      "index": 42,
      "annotations": []
    },
    {
      "index": 43,
      "annotations": [{"index": 1}]
    },
    {
      "index": 44,
      "annotations": []
    },
    {
      "index": 45,
      "annotations": [{"index": 1}]
    },
    {
      "index": 46,
      "annotations": []
    },
    {
      "index": 47,
      "annotations": [{"index": 1}]
    },
    {
      "index": 48,
      "annotations": []
    },
    {
      "index": 49,
      "annotations": [{"index": 1}]
    },
    {
      "index": 50,
      "annotations": []
    },
    {
      "index": 51,
      "annotations": [{"index": 1}]
    },
    {
      "index": 52,
      "annotations": []
    },
    {
      "index": 53,
      "annotations": [{"index": 1}]
    },
    {
      "index": 54,
      "annotations": []
    },
    {
      "index": 55,
      "annotations": [{"index": 1}]
    },
    {
      "index": 56,
      "annotations": []
    },
    {
      "index": 57,
      "annotations": [{"index": 1}]
    },
    {
      "index": 58,
      "annotations": []
    },
    {
      "index": 59,
      "annotations": [{"index": 1}]
    },
    {
      "index": 60,
      "annotations": []
    },
    {
      "index": 61,
      "annotations": [{"index": 1}]
    },
    {
      "index": 62,
      "annotations": []
    },
    {
      "index": 63,
      "annotations": [{"index": 1}]
    },
    {
      "index": 64,
      "annotations": []
    },
    {
      "index": 65,
      "annotations": [{"index": 1}]
    },
    {
      "index": 66,
      "annotations": []
    },
    {
      "index": 67,
      "annotations": [{"index": 1}]
    },
    {
      "index": 68,
      "annotations": []
    },
    {
      "index": 69,
      "annotations": [{"index": 1}]
    },
    {
      "index": 70,
      "annotations": []
    },
    {
      "index": 71,
      "annotations": [{"index": 1}]
    },
    {
      "index": 72,
      "annotations": []
    },
    {
      "index": 73,
      "annotations": [{"index": 1}]
    },
    {
      "index": 74,
      "annotations": []
    },
    {
      "index": 75,
      "annotations": [{"index": 1}]
    },
    {
      "index": 76,
      "annotations": []
    },
    {
      "index": 77,
      "annotations": [{"index": 1}]
    },
    {
      "index": 78,
      "annotations": []
    },
    {
      "index": 79,
      "annotations": [{"index": 1}]
    },
    {
      "index": 80,
      "annotations": []
    },
    {
      "index": 81,
      "annotations": [{"index": 1}]
    },
    {
      "index": 82,
      "annotations": []
    },
    {
      "index": 83,
      "annotations": [{"index": 1}]
    },
    {
      "index": 84,
      "annotations": []
    },
    {
      "index": 85,
      "annotations": [{"index": 1}]
    },
    {
      "index": 86,
      "annotations": []
    },
    {
      "index": 87,
      "annotations": [{"index": 1}]
    },
    {
      "index": 88,
      "annotations": []
    },
    {
      "index": 89,
      "annotations": [{"index": 1}]
    },
    {
      "index": 90,
      "annotations": []
    },
    {
      "index": 91,
      "annotations": [{"index": 1}]
    },
    {
      "index": 92,
      "annotations": []
    },
    {
      "index": 93,
      "annotations": [{"index": 1}]
    },
    {
      "index": 94,
      "annotations": []
    },
    {
      "index": 95,
      "annotations": [{"index": 1}]
    },
    {
      "index": 96,
      "annotations": []
    },
    {
      "index": 97,
      "annotations": [{"index": 1}]
    },
    {
      "index": 98,
      "annotations": []
    },
    {
      "index": 99,
      "annotations": [{"index": 1}]
    },
    {
      "index": 100,
      "annotations": []
    },
    {
      "index": 101,
      "annotations": [{"index": 1}]
    },
    {
      "index": 102,
      "annotations": []
    },
    {
      "index": 103,
      "annotations": [{"index": 1}]
    },
    {
      "index": 104,
      "annotations": []
    },
    {
      "index": 105,
      "annotations": [{"index": 1}]
    },
    {
      "index": 106,
      "annotations": []
    },
    {
      "index": 107,
      "annotations": [{"index": 1}]
    },
    {
      "index": 108,
      "annotations": []
    },
    {
      "index": 109,
      "annotations": [{"index": 1}]
    },
    {
      "index": 110,
      "annotations": []
    },
    {
      "index": 111,
      "annotations": [{"index": 1}]
    },
    {
      "index": 112,
      "annotations": []
    },
    {
      "index": 113,
      "annotations": [{"index": 1}]
    },
    {
      "index": 114,
      "annotations": []
    },
    {
      "index": 115,
      "annotations": [{"index": 1}]
    },
    {
      "index": 116,
      "annotations": []
    },
    {
      "index": 117,
      "annotations": [{"index": 1}]
    },
    {
      "index": 118,
      "annotations": []
    },
    {
      "index": 119,
      "annotations": [{"index": 1}]
    },
    {
      "index": 120,
      "annotations": []
    },
    {
      "index": 121,
      "annotations": [{"index": 1}]
    },
    {
      "index": 122,
      "annotations": []
    },
    {
      "index": 123,
      "annotations": [{"index": 1}]
    },
    {
      "index": 124,
      "annotations": []
    },
    {
      "index": 125,
      "annotations": [{"index": 1}]
    },
    {
      "index": 126,
      "annotations": []
    },
    {
      "index": 127,
      "annotations": [{"index": 1}]
    },
    {
      "index": 128,
      "annotations": []
    },
    {
      "index": 129,
      "annotations": [{"index": 1}]
    },
    {
      "index": 130,
      "annotations": []
    },
    {
      "index": 131,
      "annotations": [{"index": 1}]
    },
    {
      "index": 132,
      "annotations": []
    },
    {
      "index": 133,
      "annotations": [{"index": 1}]
    },
    {
      "index": 134,
      "annotations": []
    },
    {
      "index": 135,
      "annotations": [{"index": 1}]
    },
    {
      "index": 136,
      "annotations": []
    },
    {
      "index": 137,
      "annotations": [{"index": 1}]
    },
    {
      "index": 138,
      "annotations": []
    },
    {
      "index": 139,
      "annotations": [{"index": 1}]
    },
    {
      "index": 140,
      "annotations": []
    },
    {
      "index": 141,
      "annotations": [{"index": 1}]
    },
    {
      "index": 142,
      "annotations": []
    },
    {
      "index": 143,
      "annotations": [{"index": 1}]
    },
    {
      "index": 144,
      "annotations": []
    },
    {
      "index": 145,
      "annotations": [{"index": 1}]
    },
    {
      "index": 146,
      "annotations": []
    },
    {
      "index": 147,
      "annotations": [{"index": 1}]
    },
    {
      "index": 148,
      "annotations": []
    },
    {
      "index": 149,
      "annotations": [{"index": 1}]
    },
    {
      "index": 150,
      "annotations": []
    },
    {
      "index": 151,
      "annotations": [{"index": 1}]
    },
    {
      "index": 152,
      "annotations": []
    },
    {
      "index": 153,
      "annotations": [{"index": 1}]
    },
    {
      "index": 154,
      "annotations": []
    },
    {
      "index": 155,
      "annotations": [{"index": 1}]
    },
    {
      "index": 156,
      "annotations": []
    },
    {
      "index": 157,
      "annotations": [{"index": 1}]
    },
    {
      "index": 158,
      "annotations": []
    },
    {
      "index": 159,
      "annotations": [{"index": 1}]
    },
    {
      "index": 160,
      "annotations": []
    },
    {
      "index": 161,
      "annotations": [{"index": 1}]
    },
    {
      "index": 162,
      "annotations": []
    },
    {
      "index": 163,
      "annotations": [{"index": 1}]
    },
    {
      "index": 164,
      "annotations": []
    },
    {
      "index": 165,
      "annotations": [{"index": 1}]
    },
    {
      "index": 166,
      "annotations": []
    },
    {
      "index": 167,
      "annotations": [{"index": 1}]
    },
    {
      "index": 168,
      "annotations": []
    },
    {
      "index": 169,
      "annotations": [{"index": 1}]
    },
    {
      "index": 170,
      "annotations": []
    },
    {
      "index": 171,
      "annotations": []
    },
    {
      "index": 172,
      "annotations": []
    },
    {
      "index": 173,
      "annotations": []
    },
    {
      "index": 174,
      "annotations": []
    },
    {
      "index": 175,
      "annotations": []
    },
    {
      "index": 176,
      "annotations": []
    },
    {
      "index": 177,
      "annotations": []
    },
    {
      "index": 178,
      "annotations": []
    },
    {
      "index": 179,
      "annotations": []
    },
    {
      "index": 180,
      "annotations": []
    },
    {
      "index": 181,
      "annotations": []
    },
    {
      "index": 182,
      "annotations": []
    },
    {
      "index": 183,
      "annotations": []
    },
    {
      "index": 184,
      "annotations": []
    },
    {
      "index": 185,
      "annotations": []
    },
    {
      "index": 186,
      "annotations": []
    },
    {
      "index": 187,
      "annotations": []
    },
    {
      "index": 188,
      "annotations": []
    },
    {
      "index": 189,
      "annotations": []
    },
    {
      "index": 190,
      "annotations": []
    },
    {
      "index": 191,
      "annotations": []
    },
    {
      "index": 192,
      "annotations": []
    },
    {
      "index": 193,
      "annotations": []
    },
    {
      "index": 194,
      "annotations": []
    },
    {
      "index": 195,
      "annotations": []
    },
    {
      "index": 196,
      "annotations": []
    },
    {
      "index": 197,
      "annotations": []
    },
    {
      "index": 198,
      "annotations": []
    },
    {
      "index": 199,
      "annotations": []
    },
    {
      "index": 200,
      "annotations": []
    },
    {
      "index": 201,
      "annotations": []
    },
    {
      "index": 202,
      "annotations": []
    },
    {
      "index": 203,
      "annotations": []
    },
    {
      "index": 204,
      "annotations": []
    },
    {
      "index": 205,
      "annotations": []
    },
    {
      "index": 206,
      "annotations": []
    },
    {
      "index": 207,
      "annotations": []
    },
    {
      "index": 208,
      "annotations": []
    },
    {
      "index": 209,
      "annotations": []
    },
    {
      "index": 210,
      "annotations": []
    },
    {
      "index": 211,
      "annotations": []
    },
    {
      "index": 212,
      "annotations": []
    },
    {
      "index": 213,
      "annotations": []
    },
    {
      "index": 214,
      "annotations": []
    },
    {
      "index": 215,
      "annotations": []
    },
    {
      "index": 216,
      "annotations": []
    },
    {
      "index": 217,
      "annotations": []
    },
    {
      "index": 218,
      "annotations": []
    }
  ],
  "sagittal": [
    {
      "index": 1,
      "annotations": []
    },
    {
      "index": 2,
      "annotations": []
    },
    {
      "index": 3,
      "annotations": []
    },
    {
      "index": 4,
      "annotations": []
    },
    {
      "index": 5,
      "annotations": []
    },
    {
      "index": 6,
      "annotations": []
    },
    {
      "index": 7,
      "annotations": []
    },
    {
      "index": 8,
      "annotations": []
    },
    {
      "index": 9,
      "annotations": []
    },
    {
      "index": 10,
      "annotations": []
    },
    {
      "index": 11,
      "annotations": []
    },
    {
      "index": 12,
      "annotations": []
    },
    {
      "index": 13,
      "annotations": []
    },
    {
      "index": 14,
      "annotations": []
    },
    {
      "index": 15,
      "annotations": []
    },
    {
      "index": 16,
      "annotations": []
    },
    {
      "index": 17,
      "annotations": []
    },
    {
      "index": 18,
      "annotations": []
    },
    {
      "index": 19,
      "annotations": []
    },
    {
      "index": 20,
      "annotations": []
    },
    {
      "index": 21,
      "annotations": []
    },
    {
      "index": 22,
      "annotations": []
    },
    {
      "index": 23,
      "annotations": []
    },
    {
      "index": 24,
      "annotations": []
    },
    {
      "index": 25,
      "annotations": []
    },
    {
      "index": 26,
      "annotations": []
    },
    {
      "index": 27,
      "annotations": []
    },
    {
      "index": 28,
      "annotations": []
    },
    {
      "index": 29,
      "annotations": []
    },
    {
      "index": 30,
      "annotations": []
    },
    {
      "index": 31,
      "annotations": []
    },
    {
      "index": 32,
      "annotations": []
    },
    {
      "index": 33,
      "annotations": []
    },
    {
      "index": 34,
      "annotations": []
    },
    {
      "index": 35,
      "annotations": []
    },
    {
      "index": 36,
      "annotations": []
    },
    {
      "index": 37,
      "annotations": []
    },
    {
      "index": 38,
      "annotations": []
    },
    {
      "index": 39,
      "annotations": []
    },
    {
      "index": 40,
      "annotations": []
    },
    {
      "index": 41,
      "annotations": []
    },
    {
      "index": 42,
      "annotations": []
    },
    {
      "index": 43,
      "annotations": []
    },
    {
      "index": 44,
      "annotations": []
    },
    {
      "index": 45,
      "annotations": []
    },
    {
      "index": 46,
      "annotations": []
    },
    {
      "index": 47,
      "annotations": []
    },
    {
      "index": 48,
      "annotations": []
    },
    {
      "index": 49,
      "annotations": []
    },
    {
      "index": 50,
      "annotations": []
    },
    {
      "index": 51,
      "annotations": []
    },
    {
      "index": 52,
      "annotations": []
    },
    {
      "index": 53,
      "annotations": []
    },
    {
      "index": 54,
      "annotations": []
    },
    {
      "index": 55,
      "annotations": []
    },
    {
      "index": 56,
      "annotations": []
    },
    {
      "index": 57,
      "annotations": []
    },
    {
      "index": 58,
      "annotations": []
    },
    {
      "index": 59,
      "annotations": []
    },
    {
      "index": 60,
      "annotations": []
    },
    {
      "index": 61,
      "annotations": []
    },
    {
      "index": 62,
      "annotations": []
    },
    {
      "index": 63,
      "annotations": []
    },
    {
      "index": 64,
      "annotations": []
    },
    {
      "index": 65,
      "annotations": []
    },
    {
      "index": 66,
      "annotations": []
    },
    {
      "index": 67,
      "annotations": []
    },
    {
      "index": 68,
      "annotations": []
    },
    {
      "index": 69,
      "annotations": []
    },
    {
      "index": 70,
      "annotations": []
    },
    {
      "index": 71,
      "annotations": []
    },
    {
      "index": 72,
      "annotations": []
    },
    {
      "index": 73,
      "annotations": []
    },
    {
      "index": 74,
      "annotations": []
    },
    {
      "index": 75,
      "annotations": []
    },
    {
      "index": 76,
      "annotations": []
    },
    {
      "index": 77,
      "annotations": []
    },
    {
      "index": 78,
      "annotations": []
    },
    {
      "index": 79,
      "annotations": []
    },
    {
      "index": 80,
      "annotations": []
    },
    {
      "index": 81,
      "annotations": []
    },
    {
      "index": 82,
      "annotations": []
    },
    {
      "index": 83,
      "annotations": []
    },
    {
      "index": 84,
      "annotations": []
    },
    {
      "index": 85,
      "annotations": []
    },
    {
      "index": 86,
      "annotations": []
    },
    {
      "index": 87,
      "annotations": []
    },
    {
      "index": 88,
      "annotations": []
    },
    {
      "index": 89,
      "annotations": []
    },
    {
      "index": 90,
      "annotations": []
    },
    {
      "index": 91,
      "annotations": []
    },
    {
      "index": 92,
      "annotations": []
    },
    {
      "index": 93,
      "annotations": []
    },
    {
      "index": 94,
      "annotations": []
    },
    {
      "index": 95,
      "annotations": []
    },
    {
      "index": 96,
      "annotations": []
    },
    {
      "index": 97,
      "annotations": []
    },
    {
      "index": 98,
      "annotations": []
    },
    {
      "index": 99,
      "annotations": []
    },
    {
      "index": 100,
      "annotations": []
    },
    {
      "index": 101,
      "annotations": []
    },
    {
      "index": 102,
      "annotations": []
    },
    {
      "index": 103,
      "annotations": []
    },
    {
      "index": 104,
      "annotations": []
    },
    {
      "index": 105,
      "annotations": [{"index": 1}]
    },
    {
      "index": 106,
      "annotations": []
    },
    {
      "index": 107,
      "annotations": [{"index": 1}]
    },
    {
      "index": 108,
      "annotations": []
    },
    {
      "index": 109,
      "annotations": [{"index": 1}]
    },
    {
      "index": 110,
      "annotations": []
    },
    {
      "index": 111,
      "annotations": []
    },
    {
      "index": 112,
      "annotations": []
    },
    {
      "index": 113,
      "annotations": []
    },
    {
      "index": 114,
      "annotations": []
    },
    {
      "index": 115,
      "annotations": []
    },
    {
      "index": 116,
      "annotations": []
    },
    {
      "index": 117,
      "annotations": []
    },
    {
      "index": 118,
      "annotations": []
    },
    {
      "index": 119,
      "annotations": []
    },
    {
      "index": 120,
      "annotations": []
    },
    {
      "index": 121,
      "annotations": []
    },
    {
      "index": 122,
      "annotations": []
    },
    {
      "index": 123,
      "annotations": []
    },
    {
      "index": 124,
      "annotations": []
    },
    {
      "index": 125,
      "annotations": []
    },
    {
      "index": 126,
      "annotations": []
    },
    {
      "index": 127,
      "annotations": []
    },
    {
      "index": 128,
      "annotations": []
    },
    {
      "index": 129,
      "annotations": []
    },
    {
      "index": 130,
      "annotations": []
    },
    {
      "index": 131,
      "annotations": []
    },
    {
      "index": 132,
      "annotations": []
    },
    {
      "index": 133,
      "annotations": []
    },
    {
      "index": 134,
      "annotations": []
    },
    {
      "index": 135,
      "annotations": []
    },
    {
      "index": 136,
      "annotations": []
    },
    {
      "index": 137,
      "annotations": []
    },
    {
      "index": 138,
      "annotations": []
    },
    {
      "index": 139,
      "annotations": []
    },
    {
      "index": 140,
      "annotations": []
    },
    {
      "index": 141,
      "annotations": []
    },
    {
      "index": 142,
      "annotations": []
    },
    {
      "index": 143,
      "annotations": []
    },
    {
      "index": 144,
      "annotations": []
    },
    {
      "index": 145,
      "annotations": []
    },
    {
      "index": 146,
      "annotations": []
    },
    {
      "index": 147,
      "annotations": []
    },
    {
      "index": 148,
      "annotations": []
    },
    {
      "index": 149,
      "annotations": []
    },
    {
      "index": 150,
      "annotations": []
    },
    {
      "index": 151,
      "annotations": []
    },
    {
      "index": 152,
      "annotations": []
    },
    {
      "index": 153,
      "annotations": []
    },
    {
      "index": 154,
      "annotations": []
    },
    {
      "index": 155,
      "annotations": []
    },
    {
      "index": 156,
      "annotations": []
    },
    {
      "index": 157,
      "annotations": []
    },
    {
      "index": 158,
      "annotations": []
    },
    {
      "index": 159,
      "annotations": []
    },
    {
      "index": 160,
      "annotations": []
    },
    {
      "index": 161,
      "annotations": []
    },
    {
      "index": 162,
      "annotations": []
    },
    {
      "index": 163,
      "annotations": []
    },
    {
      "index": 164,
      "annotations": []
    },
    {
      "index": 165,
      "annotations": []
    },
    {
      "index": 166,
      "annotations": []
    },
    {
      "index": 167,
      "annotations": []
    },
    {
      "index": 168,
      "annotations": []
    },
    {
      "index": 169,
      "annotations": []
    },
    {
      "index": 170,
      "annotations": []
    },
    {
      "index": 171,
      "annotations": []
    },
    {
      "index": 172,
      "annotations": []
    },
    {
      "index": 173,
      "annotations": []
    },
    {
      "index": 174,
      "annotations": []
    },
    {
      "index": 175,
      "annotations": []
    },
    {
      "index": 176,
      "annotations": []
    },
    {
      "index": 177,
      "annotations": []
    },
    {
      "index": 178,
      "annotations": []
    },
    {
      "index": 179,
      "annotations": []
    },
    {
      "index": 180,
      "annotations": []
    },
    {
      "index": 181,
      "annotations": []
    },
    {
      "index": 182,
      "annotations": []
    },
    {
      "index": 183,
      "annotations": []
    },
    {
      "index": 184,
      "annotations": []
    },
    {
      "index": 185,
      "annotations": []
    },
    {
      "index": 186,
      "annotations": []
    },
    {
      "index": 187,
      "annotations": []
    },
    {
      "index": 188,
      "annotations": []
    },
    {
      "index": 189,
      "annotations": []
    },
    {
      "index": 190,
      "annotations": []
    },
    {
      "index": 191,
      "annotations": []
    },
    {
      "index": 192,
      "annotations": []
    },
    {
      "index": 193,
      "annotations": []
    },
    {
      "index": 194,
      "annotations": []
    },
    {
      "index": 195,
      "annotations": []
    },
    {
      "index": 196,
      "annotations": []
    },
    {
      "index": 197,
      "annotations": []
    },
    {
      "index": 198,
      "annotations": []
    },
    {
      "index": 199,
      "annotations": []
    },
    {
      "index": 200,
      "annotations": []
    },
    {
      "index": 201,
      "annotations": []
    },
    {
      "index": 202,
      "annotations": []
    },
    {
      "index": 203,
      "annotations": []
    },
    {
      "index": 204,
      "annotations": []
    },
    {
      "index": 205,
      "annotations": []
    },
    {
      "index": 206,
      "annotations": []
    },
    {
      "index": 207,
      "annotations": []
    },
    {
      "index": 208,
      "annotations": []
    },
    {
      "index": 209,
      "annotations": []
    },
    {
      "index": 210,
      "annotations": []
    },
    {
      "index": 211,
      "annotations": []
    },
    {
      "index": 212,
      "annotations": []
    },
    {
      "index": 213,
      "annotations": []
    },
    {
      "index": 214,
      "annotations": []
    },
    {
      "index": 215,
      "annotations": []
    },
    {
      "index": 216,
      "annotations": []
    },
    {
      "index": 217,
      "annotations": []
    },
    {
      "index": 218,
      "annotations": []
    }
  ]
}